pylabframe/__init__.py
pylabframe/config.py
pylabframe/general.py
pylabframe/util.py
pylabframe/data/__init__.py
pylabframe/data/core.py
pylabframe/data/fitters.py
pylabframe/data/helpers.py
pylabframe/data/path.py
pylabframe/data/loaders/__init__.py
pylabframe/data/loaders/keysight_loader.py
pylabframe/hw/__init__.py
pylabframe/hw/device.py
pylabframe/hw/visadevice.py
pylabframe/hw/drivers/__init__.py
pylabframe/hw/drivers/keysightvisa.py
pylabframe/hw/drivers/redpitaya.py
pylabframe/hw/drivers/rigolvisa.py
pylabframe/hw/drivers/santecvisa.py
pylabframe/hw/drivers/siglentvisa.py
pylabframe/hw/drivers/tekvisa.py
pylabframe/hw/drivers/thorlabsvisa.py
pylabframe-0.0.5.dist-info/METADATA
pylabframe-0.0.5.dist-info/WHEEL
pylabframe-0.0.5.dist-info/licenses/LICENSE
pylabframe-0.0.5.dist-info/RECORD
