Metadata-Version: 2.3
Name: pylabframe
Version: 0.0.5
Summary: Python package to interact with laboratory devices and measurement data
Project-URL: Homepage, https://github.com/JesseSlim/pylabframe
Project-URL: Bug Tracker, https://github.com/JesseSlim/pylabframe/issues
Author-email: Jesse Slim <jesse.j.slim@gmail.com>
License-File: LICENSE
Classifier: License :: OSI Approved :: MIT License
Classifier: Operating System :: OS Independent
Classifier: Programming Language :: Python :: 3
Requires-Python: >=3.7
Requires-Dist: matplotlib
Requires-Dist: numpy
Requires-Dist: tomli; python_version < '3.11'
